LICENSE
MANIFEST.in
README.rst
setup.cfg
setup.py
django_edgecast/__init__.py
django_edgecast/models.py
edgecast/__init__.py
edgecast.egg-info/PKG-INFO
edgecast.egg-info/SOURCES.txt
edgecast.egg-info/dependency_links.txt
edgecast.egg-info/requires.txt
edgecast.egg-info/top_level.txt
edgecast.egg-info/zip-safe