Metadata-Version: 1.0
Name: edgecast
Version: 1.0.2
Summary: Convenient EdgeCast CDN management for Python
Home-page: http://bruun.co/
Author: Nick Bruun
Author-email: nick@bruun.co
License: Copyright 2013 Nick Bruun <nick@bruun.co>
